{
  "lottery": "laos_develops",
  "lottery_name": "หวยลาวพัฒนา",
  "source_url": "https://exphuay.com/calculate/laosdevelops",
  "fetched_at": "2026-02-16T17:25:36.231Z",
  "window": {
    "latest_n_draws": 30
  },
  "daily_calculation": {
    "top3": [
      "043",
      "682",
      "430",
      "830",
      "482"
    ],
    "top3_recommended": [
      "043",
      "430",
      "830"
    ],
    "bottom2": [
      "76",
      "44",
      "39",
      "08",
      "46",
      "03"
    ],
    "bottom2_recommended": [
      "44",
      "46"
    ],
    "running_number": "4",
    "full_set_number": "3"
  },
  "digit_frequency": {
    "data": []
  },
  "statistics_30_draws": {
    "bottom2": [
      {
        "number": "26",
        "count": 1
      },
      {
        "number": "30",
        "count": 1
      },
      {
        "number": "34",
        "count": 1
      },
      {
        "number": "38",
        "count": 1
      },
      {
        "number": "41",
        "count": 1
      },
      {
        "number": "45",
        "count": 2
      },
      {
        "number": "46",
        "count": 1
      },
      {
        "number": "48",
        "count": 1
      },
      {
        "number": "55",
        "count": 1
      },
      {
        "number": "59",
        "count": 1
      },
      {
        "number": "64",
        "count": 2
      },
      {
        "number": "67",
        "count": 1
      },
      {
        "number": "70",
        "count": 2
      },
      {
        "number": "74",
        "count": 1
      },
      {
        "number": "76",
        "count": 1
      },
      {
        "number": "77",
        "count": 1
      },
      {
        "number": "78",
        "count": 1
      },
      {
        "number": "80",
        "count": 2
      },
      {
        "number": "84",
        "count": 1
      },
      {
        "number": "91",
        "count": 1
      },
      {
        "number": "96",
        "count": 1
      },
      {
        "number": "09",
        "count": 2
      },
      {
        "number": "03",
        "count": 1
      },
      {
        "number": "00",
        "count": 1
      }
    ],
    "top3": [
      {
        "number": "145",
        "count": 1
      },
      {
        "number": "182",
        "count": 1
      },
      {
        "number": "369",
        "count": 1
      },
      {
        "number": "401",
        "count": 1
      },
      {
        "number": "430",
        "count": 1
      },
      {
        "number": "439",
        "count": 1
      },
      {
        "number": "440",
        "count": 1
      },
      {
        "number": "469",
        "count": 1
      },
      {
        "number": "509",
        "count": 1
      },
      {
        "number": "541",
        "count": 1
      },
      {
        "number": "546",
        "count": 1
      },
      {
        "number": "603",
        "count": 1
      },
      {
        "number": "626",
        "count": 1
      },
      {
        "number": "653",
        "count": 1
      },
      {
        "number": "662",
        "count": 1
      },
      {
        "number": "685",
        "count": 1
      },
      {
        "number": "753",
        "count": 1
      },
      {
        "number": "789",
        "count": 1
      },
      {
        "number": "817",
        "count": 1
      },
      {
        "number": "845",
        "count": 1
      },
      {
        "number": "892",
        "count": 1
      },
      {
        "number": "905",
        "count": 1
      },
      {
        "number": "932",
        "count": 1
      },
      {
        "number": "963",
        "count": 1
      },
      {
        "number": "073",
        "count": 1
      },
      {
        "number": "085",
        "count": 1
      },
      {
        "number": "039",
        "count": 1
      },
      {
        "number": "060",
        "count": 1
      },
      {
        "number": "052",
        "count": 1
      },
      {
        "number": "099",
        "count": 1
      }
    ]
  },
  "notes": "อ่านข้อมูลจากรูป calc.png + stat.png ด้วย AI Vision"
}